{"cameraMode":{"drawMode":0,"name":"Shaded","section":"Shading Mode"},"sceneLighting":false,"audioPlay":false,"sceneViewState":{"m_AlwaysRefresh":false,"showFog":true,"showSkybox":false,"showFlares":true,"showImageEffects":true,"showParticleSystems":true,"showVisualEffectGraphs":true,"m_FxEnabled":true},"in2DMode":false,"pivot":{"x":-25.0,"y":1.0,"z":25.0},"rotation":{"x":-0.45804107189178469,"y":0.009846189059317112,"z":-0.005081848241388798,"w":-0.8888840675354004},"size":1.2247449159622193,"orthographic":false}